blognajd/__init__.py
blognajd/admin.py
blognajd/context_processors.py
blognajd/feeds.py
blognajd/forms.py
blognajd/models.py
blognajd/sitemaps.py
blognajd/urls.py
blognajd/views.py
blognajd/conf/__init__.py
blognajd/conf/defaults.py
blognajd/migrations/0001_initial.py
blognajd/migrations/0002_auto_20150825_0829.py
blognajd/migrations/0003_sitesettings_theme.py
blognajd/migrations/0004_auto_20150904_1506.py
blognajd/migrations/__init__.py
blognajd/static/blognajd/css/theme.css
blognajd/static/blognajd/themes/default/css/bootstrap.min.css
blognajd/static/blognajd/themes/default/css/theme.css
blognajd/static/blognajd/themes/default/css/theme.css~
blognajd/static/blognajd/themes/default/css/theme.webarchive
blognajd/static/blognajd/themes/default/css/theme.webarchive~
blognajd/static/js/bootstrap.min.js
blognajd/static/js/html5shiv.js
blognajd/static/js/respond.min.js
blognajd/templates/blognajd/403.html
blognajd/templates/blognajd/404.html
blognajd/templates/blognajd/500.html
blognajd/templates/blognajd/about.html
blognajd/templates/blognajd/base.html
blognajd/templates/blognajd/blog.html
blognajd/templates/blognajd/index.html
blognajd/templates/blognajd/projects.html
blognajd/templates/blognajd/story_archive_year.html
blognajd/templates/blognajd/story_detail.html
blognajd/templates/blognajd/tag_detail.html
blognajd/templates/blognajd/tag_list.html
blognajd/templates/blognajd/includes/comments.html
blognajd/templates/blognajd/includes/comments_for_object.html
blognajd/templates/blognajd/includes/projects.html
blognajd/templates/blognajd/includes/projects.html~
blognajd/templates/blognajd/includes/story_archive.html
blognajd/templates/blognajd/includes/story_blog.html
blognajd/templates/blognajd/includes/story_index.html
blognajd/templates/blognajd/includes/subscribe_block.html
blognajd/templates/comments/posted.html
blognajd/templates/comments/blognajd/comment.html
blognajd/templates/comments/blognajd/form.html
blognajd-1.1.1.dist-info/DESCRIPTION.rst
blognajd-1.1.1.dist-info/METADATA
blognajd-1.1.1.dist-info/metadata.json
blognajd-1.1.1.dist-info/RECORD
blognajd-1.1.1.dist-info/top_level.txt
blognajd-1.1.1.dist-info/WHEEL
